{
    "tool_name": "百度百科-免费API",
    "tool_description": "百度百科词条卡片API",
    "home_url": "https://www.free-api.com/doc/552",
    "country": "China",
    "api_list": [
        {
            "name": "百度百科词条卡片API",
            "url": "https://baike.baidu.com/api/openapi/BaikeLemmaCardApi",
            "description": "获取百度百科词条卡片信息",
            "method": "GET",
            "required_parameters": [
                {
                    "name": "appid",
                    "type": "int",
                    "description": "api_key",
                    "default": "379020"
                },
                {
                    "name": "bk_key",
                    "type": "string",
                    "description": "百度百科关键词",
                    "default": "接口"
                }
            ],
            "optional_parameters": [],
            "statuscode": "200",
            "schema": {}
        }
    ]
}